mobtimer/__init__.py
mobtimer/macos.py
mobtimer-1.1.3.dist-info/METADATA
mobtimer-1.1.3.dist-info/WHEEL
mobtimer-1.1.3.dist-info/entry_points.txt
mobtimer-1.1.3.dist-info/top_level.txt
mobtimer-1.1.3.dist-info/RECORD
